quick_doc_py/__init__.py
quick_doc_py/config.py
quick_doc_py/log_logic/req.py
quick_doc_py/main.py
quick_doc_py/providers_test.py
quick_doc_py/utilities.py
quick_doc_py-1.1.9.dist-info/entry_points.txt
quick_doc_py-1.1.9.dist-info/LICENSE
quick_doc_py-1.1.9.dist-info/METADATA
quick_doc_py-1.1.9.dist-info/WHEEL
quick_doc_py-1.1.9.dist-info/RECORD
