Metadata-Version: 2.1
Name: quick-doc-py
Version: 1.1.9
Summary: This code can make documentation for your project
Home-page: https://github.com/Drag-GameStudio/Quick-Documentation
License: MIT
Author: Dmytro
Author-email: sinica911@gmail.com
Requires-Python: >=3.10,<4.0
Classifier: License :: OSI Approved :: MIT License
Classifier: Programming Language :: Python :: 3
Classifier: Programming Language :: Python :: 3.10
Classifier: Programming Language :: Python :: 3.11
Classifier: Programming Language :: Python :: 3.12
Classifier: Programming Language :: Python :: 3.13
Requires-Dist: colorama (>=0.4.6,<0.5.0)
Requires-Dist: g4f (>=0.4.0.4,<0.5.0.0)
Requires-Dist: requests (>=2.32.3,<3.0.0)
Project-URL: Repository, https://github.com/Drag-GameStudio/Quick-Documentation
